static_osm_indexer/extract_road_network.py
static_osm_indexer/generate_full_map.py
static_osm_indexer/generate_mbtiles.py
static_osm_indexer/helpers.py
static_osm_indexer/index_locations_names.py
static_osm_indexer/list_named_locations.py
static_osm_indexer/road_network_to_geojson.py
static_osm_indexer/static_assets/index.html
static_osm_indexer/static_assets/maplibre-gl.css
static_osm_indexer/static_assets/maplibre-gl.js
static_osm_indexer/static_assets/osm_liberty.json
static_osm_indexer/static_assets/text_search.bundle.js
static_osm_indexer/static_assets/tilemaker_config.json
static_osm_indexer-0.2.1.dist-info/METADATA
static_osm_indexer-0.2.1.dist-info/WHEEL
static_osm_indexer-0.2.1.dist-info/entry_points.txt
static_osm_indexer-0.2.1.dist-info/top_level.txt
static_osm_indexer-0.2.1.dist-info/RECORD
