Metadata-Version: 2.1
Name: static-osm-indexer
Version: 0.2.1
Summary: Tool to process OSM files, mainly for static sites
Author-email: Jacopo Farina <jacopo1.farina@gmail.com>
Maintainer-email: Jacopo Farina <jacopo1.farina@gmail.com>
License: MIT License
Project-URL: Homepage, https://github.com/jacopofar/static-osm-indexer
Project-URL: Bug Tracker, https://github.com/jacopofar/static-osm-indexer/issues
Classifier: Programming Language :: Python :: 3
Classifier: Development Status :: 3 - Alpha
Classifier: License :: OSI Approved :: MIT License
Classifier: Operating System :: OS Independent
Classifier: Topic :: Scientific/Engineering :: GIS
Requires-Python: >=3.9
Requires-Dist: osmium (>=3.4.0)
Requires-Dist: click (>=8.1.0)
Requires-Dist: shapely (==2.0b2)
Requires-Dist: geopy (==2.3.0)
Provides-Extra: testing
Requires-Dist: coverage ; extra == 'testing'
Requires-Dist: pytest (>=7.2.0) ; extra == 'testing'
Requires-Dist: mypy (>=0.990) ; extra == 'testing'
Requires-Dist: pytest-cov (>=4.0.0) ; extra == 'testing'
Requires-Dist: black ; extra == 'testing'
Requires-Dist: mypy ; extra == 'testing'
